MANIFEST.in
README.txt
setup.py
svn-commit.tmp
ncdr/NCDR.py
ncdr/__init__.py
ncdr.egg-info/PKG-INFO
ncdr.egg-info/SOURCES.txt
ncdr.egg-info/dependency_links.txt
ncdr.egg-info/top_level.txt