Metadata-Version: 1.0
Name: ncdr
Version: 0.0.8
Summary: UNKNOWN
Home-page: http://www.stoneworksolutions.net
Author: StoneworkSolutions
Author-email: desarrollo@stoneworksolutions.net
License: UNKNOWN
Platform: UNKNOWN
